gallery_dvk/__init__.py
gallery_dvk/config.py
gallery_dvk/gallery_dvk.py
gallery_dvk/extractor/__init__.py
gallery_dvk/extractor/docslab.py
gallery_dvk/extractor/extractor.py
gallery_dvk/extractor/kemonocafe.py
gallery_dvk/extractor/overflowingbra.py
gallery_dvk/extractor/tgcomics.py
gallery_dvk/extractor/transfur.py
gallery_dvk/extractor/webtoon.py
gallery_dvk/test/__init__.py
gallery_dvk/test/test_config.py
gallery_dvk/test/test_gallery_dvk.py
gallery_dvk/test/extractor/__init__.py
gallery_dvk/test/extractor/dummy_extractor.py
gallery_dvk/test/extractor/test_docslab.py
gallery_dvk/test/extractor/test_extractor.py
gallery_dvk/test/extractor/test_kemonocafe.py
gallery_dvk/test/extractor/test_overflowingbra.py
gallery_dvk/test/extractor/test_tgcomics.py
gallery_dvk/test/extractor/test_transfur.py
gallery_dvk/test/extractor/test_webtoon.py
gallery_dvk-0.5.1.dist-info/licenses/LICENSE
gallery_dvk-0.5.1.dist-info/METADATA
gallery_dvk-0.5.1.dist-info/WHEEL
gallery_dvk-0.5.1.dist-info/entry_points.txt
gallery_dvk-0.5.1.dist-info/top_level.txt
gallery_dvk-0.5.1.dist-info/RECORD
