Metadata-Version: 2.4
Name: gallery-dvk
Version: 0.5.1
Summary: Utility for downloading media from various image hosting websites.
Home-page: https://github.com/Drakovek/gallery-dvk
Author: Drakovek
Author-email: DrakovekMail@gmail.com
Classifier: Programming Language :: Python :: 3
Classifier: License :: OSI Approved :: GNU General Public License v3 (GPLv3)
Classifier: Operating System :: OS Independent
Requires-Python: >=3.0
License-File: LICENSE
Requires-Dist: beautifulsoup4
Requires-Dist: HTML-String-Tools
Requires-Dist: html5lib
Requires-Dist: Metadata-Magic
Requires-Dist: Pillow
Requires-Dist: Python-Print-Tools
Requires-Dist: requests
Requires-Dist: tqdm
Dynamic: author
Dynamic: author-email
Dynamic: classifier
Dynamic: description
Dynamic: description-content-type
Dynamic: home-page
Dynamic: license-file
Dynamic: requires-dist
Dynamic: requires-python
Dynamic: summary
